polarsai/__init__.py
polarsai/helpers/__init__.py
polarsai/helpers/_optional.py
polarsai/helpers/cache.py
polarsai/helpers/constants.py
polarsai/helpers/exceptions.py
polarsai/helpers/from_excel.py
polarsai/helpers/notebook.py
polarsai/helpers/save_chart.py
polarsai/helpers/shortcuts.py
polarsai/llm/__init__.py
polarsai/llm/base.py
polarsai/llm/langchain_base.py
polarsai/prompts/__init__.py
polarsai/prompts/base.py
polarsai/prompts/correct_error_prompt.py
polarsai/prompts/correct_multiples_prompt.py
polarsai/prompts/generate_python_code.py
polarsai/prompts/generate_response.py
polarsai/prompts/multiple_dataframes.py
polarsai-0.0.32.dist-info/LICENSE
polarsai-0.0.32.dist-info/METADATA
polarsai-0.0.32.dist-info/WHEEL
polarsai-0.0.32.dist-info/top_level.txt
polarsai-0.0.32.dist-info/RECORD
